tarz/__init__.py
tarz/core.py
tarz-1.0.dist-info/LICENSE
tarz-1.0.dist-info/METADATA
tarz-1.0.dist-info/WHEEL
tarz-1.0.dist-info/top_level.txt
tarz-1.0.dist-info/RECORD
