Metadata-Version: 2.1
Name: tarz
Version: 1.0
Summary: TArz is a Python package designed for tracking real-time cryptocurrency prices and gold prices from trusted sources. Whether you are a crypto enthusiast or just need the latest price of gold, TArz offers an easy-to-use interface for fetching live prices. With TArz, you can access a wide range of cryptocurrencies and gold prices directly within your Python applications.
Author: Tahagaga
License: MIT
Keywords: crypto,bitcoin,gold,finance,python
Classifier: Programming Language :: Python :: 3
Classifier: License :: OSI Approved :: MIT License
Classifier: Operating System :: OS Independent
Requires-Python: >=3.6
License-File: LICENSE
Requires-Dist: requests
Requires-Dist: beautifulsoup4
